.gitignore
.readthedocs.yml
LICENSE
README.rst
contributing.rst
pyproject.toml
setup.py
tox.ini
.github/workflows/ci.yml
arcesetc/__init__.py
arcesetc/conftest.py
arcesetc/plots.py
arcesetc/util.py
arcesetc/version.py
arcesetc.egg-info/PKG-INFO
arcesetc.egg-info/SOURCES.txt
arcesetc.egg-info/dependency_links.txt
arcesetc.egg-info/not-zip-safe
arcesetc.egg-info/requires.txt
arcesetc.egg-info/top_level.txt
arcesetc/data/BD28_4211.0026.wfrmcpc.fits
arcesetc/data/HIP107864.0003.wfrmcpc.fits
arcesetc/data/HR5191.0002.wfrmcpc.fits
arcesetc/data/README.rst
arcesetc/data/archive.hdf5
arcesetc/data/sptype_dict.json
arcesetc/data/sptype_to_temp.json
arcesetc/tests/__init__.py
arcesetc/tests/test_utils.py
docs/.rtd_environment.yaml
docs/Makefile
docs/conf.py
docs/index.rst
docs/paper.bib
docs/paper.md
docs/_build/html/_downloads/1285442fc69ec296739193a5bb01cfd3/gettingstarted-4.py
docs/_build/html/_downloads/134ab96a9d43a359afd7287f2aa43fe5/gettingstarted-4.py
docs/_build/html/_downloads/841caadd042d58ca8a1c4363a8e368a7/gettingstarted-2.py
docs/_build/html/_downloads/b66b1a2ed9b3ca7d529871c1355618c7/gettingstarted-1.py
docs/_build/html/_downloads/c5ac9a86f2a29263110f45bf565f7bd4/gettingstarted-3.py
docs/_build/html/_downloads/d90ff9160e5ef651bae7944605ca23d4/gettingstarted-1.py
docs/_build/html/_downloads/d97ef3d967eb2cc595a6a4c3ad1454e7/gettingstarted-2.py
docs/_build/html/_downloads/da6f961d2f854338ba956b87cf0e425a/gettingstarted-3.py
docs/_build/html/plot_directive/arcesetc/gettingstarted-1.py
docs/_build/html/plot_directive/arcesetc/gettingstarted-2.py
docs/_build/html/plot_directive/arcesetc/gettingstarted-3.py
docs/_build/html/plot_directive/arcesetc/gettingstarted-4.py
docs/_templates/autosummary/base.rst
docs/_templates/autosummary/class.rst
docs/_templates/autosummary/module.rst
docs/arcesetc/cmd.png
docs/arcesetc/gettingstarted.rst
docs/arcesetc/index.rst
docs/arcesetc/installation.rst
docs/arcesetc/nextsteps.rst
licenses/APACHE2.rst
licenses/BSD2.rst
licenses/BSD3.rst
licenses/GPLv3.rst
licenses/MIT.rst
licenses/README.rst
licenses/TEMPLATE_LICENCE.rst
notebooks/example.ipynb