Metadata-Version: 2.1
Name: arcesetc
Version: 0.3
Summary: Exposure time calculator for APO/ARCES
Author: Trevor Dorn-Wallenstein
Author-email: Brett Morris <morrisbrettm@gmail.com>
License: MIT License
Project-URL: repository, https://github.com/bmorris3/arcesetc
Requires-Python: >=3.5
Provides-Extra: test
Provides-Extra: docs
License-File: LICENSE
